img_processing_priferr/__init__.py
img_processing_priferr/processing/__init__.py
img_processing_priferr/processing/combine.py
img_processing_priferr/processing/transform.py
img_processing_priferr/utils/__init__.py
img_processing_priferr/utils/io.py
img_processing_priferr/utils/plot.py
img_processing_priferr-0.0.1.dist-info/METADATA
img_processing_priferr-0.0.1.dist-info/WHEEL
img_processing_priferr-0.0.1.dist-info/top_level.txt
img_processing_priferr-0.0.1.dist-info/RECORD
