Metadata-Version: 2.1
Name: img-processing-priferr
Version: 0.0.1
Summary: Study Image Processing Using Skimage
Home-page: https://github.com/priferr/img_processing_pkg
Author: priferr
Author-email: ipriferr@gmail.com
Requires-Python: >=3.5
Requires-Dist: matplotlib
Requires-Dist: numpy
Requires-Dist: scikit-image>=0.16.1
